squp/DataConversion.py
squp/GuiManual.py
squp/SplinterShortcuts.py
squp/SystemShortcuts.py
squp/UpdateGui.py
squp/__init__.py
squp/command_line.py
squp/email_script.py
squp/information.py
squp/interface.py
squp/shortcuts.py
squp-0.1.8.dist-info/LICENSE
squp-0.1.8.dist-info/LICENSE.txt
squp-0.1.8.dist-info/METADATA
squp-0.1.8.dist-info/WHEEL
squp-0.1.8.dist-info/entry_points.txt
squp-0.1.8.dist-info/top_level.txt
squp-0.1.8.dist-info/RECORD
