Metadata-Version: 2.1
Name: squp
Version: 0.1.8
Summary: A backend engine for Squarespace that uses splinter/selenium for automated data entry
Home-page: https://github.com/Ninjaura314/squp
Author: Jonathan Hoyle
Author-email: jonathanhoyle314@gmail.com
License: Mozilla Public License 2.0 (MPL 2.0)
Keywords: ecommerce automation web splinter selenium squarespace
Platform: UNKNOWN
Classifier: Development Status :: 4 - Beta
Classifier: Programming Language :: Python :: 3.7
Classifier: Intended Audience :: End Users/Desktop
Classifier: Environment :: Win32 (MS Windows)
Classifier: Intended Audience :: Customer Service
Classifier: License :: OSI Approved :: Mozilla Public License 2.0 (MPL 2.0)
Classifier: Topic :: Software Development :: User Interfaces
Classifier: Topic :: Internet :: WWW/HTTP :: Browsers
Classifier: Topic :: Internet :: WWW/HTTP :: Dynamic Content
Classifier: Topic :: Internet :: WWW/HTTP :: Session
Classifier: Topic :: Internet :: WWW/HTTP :: Site Management
Classifier: Topic :: Internet :: WWW/HTTP :: Site Management :: Link Checking
Requires-Dist: addict
Requires-Dist: ahk
Requires-Dist: appJar
Requires-Dist: arrow
Requires-Dist: beautifulsoup4
Requires-Dist: bottle
Requires-Dist: colour
Requires-Dist: dataset
Requires-Dist: docker
Requires-Dist: dominate
Requires-Dist: ftfy
Requires-Dist: lxml
Requires-Dist: pillow
Requires-Dist: pyautogui
Requires-Dist: pypiwin32
Requires-Dist: pywebview
Requires-Dist: pywin32
Requires-Dist: scrapy
Requires-Dist: selenium
Requires-Dist: splinter
Requires-Dist: urllib3
